{"_id":"51dd8f96acdac79a22bc8e7a","anyone_authority":"r","branch":{"master":{"HEAD":{"history":[{"ope":{"operation":"updateproperty","instanceURI":"root.classes.k17v4n53mu00e","propertyName":"name","value":"counter_clerk"},"created":"2013-07-10T16:47:02.105Z","user":"51636b6a6dcb72db18000002"}],"model":{"root":{"_connections":{"j17v4njgg1002":{"_sys_exist":true,"_sys_id":"","_sys_meta":"Editor.DiagramEditor.Connection","_sys_name":"j17v4njgg1002","_sys_parent_uri":"root._connections","color":"","ex":"","ey":"","sx":"","sy":"","uri":"root.classes.k17v4n53mu001.srcAssociations.j17v4njgg1001","x1":"","x2":"","x3":"","y1":"","y2":"","y3":""},"j17v4njgg1004":{"_sys_exist":true,"_sys_id":"","_sys_meta":"Editor.DiagramEditor.Connection","_sys_name":"j17v4njgg1004","_sys_parent_uri":"root._connections","color":"","ex":"","ey":"","sx":"","sy":"","uri":"root.classes.k17v4n53mu001.srcAssociations.j17v4njgg1003","x1":"","x2":"","x3":"","y1":"","y2":"","y3":""},"j17v4njgg1006":{"_sys_exist":true,"_sys_id":"","_sys_meta":"Editor.DiagramEditor.Connection","_sys_name":"j17v4njgg1006","_sys_parent_uri":"root._connections","color":"","ex":"","ey":"","sx":"","sy":"","uri":"root.classes.k17v4n53mu00g.srcAssociations.j17v4njgg1005","x1":"","x2":"","x3":"","y1":"","y2":"","y3":""},"j17v4njgg1008":{"_sys_exist":true,"_sys_id":"","_sys_meta":"Editor.DiagramEditor.Connection","_sys_name":"j17v4njgg1008","_sys_parent_uri":"root._connections","color":"","ex":"","ey":"","sx":"","sy":"","uri":"root.classes.k17v4n53mu00g.srcAssociations.j17v4njgg1007","x1":"","x2":"","x3":"","y1":"","y2":"","y3":""},"k17v4n53mu00n":{"_sys_exist":true,"_sys_id":"","_sys_meta":"Editor.DiagramEditor.Connection","_sys_name":"k17v4n53mu00n","_sys_parent_uri":"root._connections","color":"","ex":"","ey":"","sx":"","sy":"","uri":"root.classes.k17v4n53mu00e.srcAssociations.k17v4n53mu00m","x1":"","x2":"","x3":"","y1":"","y2":"","y3":""},"k17v4n53mu00p":{"_sys_exist":true,"_sys_id":"","_sys_meta":"Editor.DiagramEditor.Connection","_sys_name":"k17v4n53mu00p","_sys_parent_uri":"root._connections","color":"","ex":"","ey":"","sx":"","sy":"","uri":"root.classes.k17v4n53mu00e.srcAssociations.k17v4n53mu00o","x1":"","x2":"","x3":"","y1":"","y2":"","y3":""}},"_nodes":{"k17v4n53mu002":{"_sys_exist":true,"_sys_id":"","_sys_meta":"Editor.DiagramEditor.Node","_sys_name":"k17v4n53mu002","_sys_parent_uri":"root._nodes","color":"","h":null,"uri":"root.classes.k17v4n53mu001","w":null,"x":304,"y":68},"k17v4n53mu005":{"_sys_exist":true,"_sys_id":"","_sys_meta":"Editor.DiagramEditor.Node","_sys_name":"k17v4n53mu005","_sys_parent_uri":"root._nodes","color":"","h":null,"uri":"root.classes.k17v4n53mu004","w":null,"x":459,"y":68},"k17v4n53mu00a":{"_sys_exist":true,"_sys_id":"","_sys_meta":"Editor.DiagramEditor.Node","_sys_name":"k17v4n53mu00a","_sys_parent_uri":"root._nodes","color":"","h":null,"uri":"root.classes.k17v4n53mu009","w":null,"x":292,"y":200},"k17v4n53mu00f":{"_sys_exist":true,"_sys_id":"","_sys_meta":"Editor.DiagramEditor.Node","_sys_name":"k17v4n53mu00f","_sys_parent_uri":"root._nodes","color":"","h":null,"uri":"root.classes.k17v4n53mu00e","w":null,"x":134,"y":72},"k17v4n53mu00h":{"_sys_exist":true,"_sys_id":"","_sys_meta":"Editor.DiagramEditor.Node","_sys_name":"k17v4n53mu00h","_sys_parent_uri":"root._nodes","color":"","h":null,"uri":"root.classes.k17v4n53mu00g","w":null,"x":133,"y":185},"k17v4n53mu00j":{"_sys_exist":true,"_sys_id":"","_sys_meta":"Editor.DiagramEditor.Node","_sys_name":"k17v4n53mu00j","_sys_parent_uri":"root._nodes","color":"","h":null,"uri":"root.classes.k17v4n53mu00i","w":null,"x":118,"y":339},"k17v4n53mu00l":{"_sys_exist":true,"_sys_id":"","_sys_meta":"Editor.DiagramEditor.Node","_sys_name":"k17v4n53mu00l","_sys_parent_uri":"root._nodes","color":"","h":null,"uri":"root.classes.k17v4n53mu00k","w":null,"x":3,"y":189}},"_sys_exist":true,"_sys_id":"","_sys_meta":"simpleclassdiagram.ClassDiagram","_sys_name":"root","_sys_parent_uri":null,"_sys_root":true,"classes":{"k17v4n53mu001":{"_sys_exist":true,"_sys_id":"name","_sys_meta":"simpleclassdiagram.Class","_sys_name":"k17v4n53mu001","_sys_parent_uri":"root.classes","attr":{"k17v4n53mu003":{"_sys_name":"k17v4n53mu003","_sys_meta":"simpleclassdiagram.Attribute","_sys_exist":true,"_sys_parent_uri":"root.classes.k17v4n53mu001.attr","_sys_id":"name","name":"","type":""}},"name":"customer_manager","operation":{},"srcAssociations":{"j17v4njgg1001":{"_sys_exist":true,"_sys_id":"","_sys_meta":"simpleclassdiagram.Association","_sys_name":"j17v4njgg1001","_sys_parent_uri":"root.classes.k17v4n53mu001.srcAssociations","source":"root.classes.k17v4n53mu001","target":"root.classes.k17v4n53mu009"},"j17v4njgg1003":{"_sys_exist":true,"_sys_id":"","_sys_meta":"simpleclassdiagram.Association","_sys_name":"j17v4njgg1003","_sys_parent_uri":"root.classes.k17v4n53mu001.srcAssociations","source":"root.classes.k17v4n53mu001","target":"root.classes.k17v4n53mu004"}},"srcGeneralization":{}},"k17v4n53mu004":{"_sys_exist":true,"_sys_id":"name","_sys_meta":"simpleclassdiagram.Class","_sys_name":"k17v4n53mu004","_sys_parent_uri":"root.classes","attr":{"k17v4n53mu006":{"_sys_exist":true,"_sys_id":"name","_sys_meta":"simpleclassdiagram.Attribute","_sys_name":"k17v4n53mu006","_sys_parent_uri":"root.classes.k17v4n53mu004.attr","name":"date","type":"datetime"},"k17v4n53mu007":{"_sys_exist":true,"_sys_id":"name","_sys_meta":"simpleclassdiagram.Attribute","_sys_name":"k17v4n53mu007","_sys_parent_uri":"root.classes.k17v4n53mu004.attr","name":"content","type":"string"},"k17v4n53mu008":{"_sys_exist":true,"_sys_id":"name","_sys_meta":"simpleclassdiagram.Attribute","_sys_name":"k17v4n53mu008","_sys_parent_uri":"root.classes.k17v4n53mu004.attr","name":"title","type":"string"}},"name":"deal_info","operation":{},"srcAssociations":{},"srcGeneralization":{}},"k17v4n53mu009":{"_sys_exist":true,"_sys_id":"name","_sys_meta":"simpleclassdiagram.Class","_sys_name":"k17v4n53mu009","_sys_parent_uri":"root.classes","attr":{"k17v4n53mu00b":{"_sys_exist":true,"_sys_id":"name","_sys_meta":"simpleclassdiagram.Attribute","_sys_name":"k17v4n53mu00b","_sys_parent_uri":"root.classes.k17v4n53mu009.attr","name":"name","type":"string"},"k17v4n53mu00c":{"_sys_exist":true,"_sys_id":"name","_sys_meta":"simpleclassdiagram.Attribute","_sys_name":"k17v4n53mu00c","_sys_parent_uri":"root.classes.k17v4n53mu009.attr","name":"address","type":"string"},"k17v4n53mu00d":{"_sys_exist":true,"_sys_id":"name","_sys_meta":"simpleclassdiagram.Attribute","_sys_name":"k17v4n53mu00d","_sys_parent_uri":"root.classes.k17v4n53mu009.attr","name":"tel","type":"string"}},"name":"customer_info","operation":{},"srcAssociations":{},"srcGeneralization":{}},"k17v4n53mu00e":{"_sys_exist":true,"_sys_id":"name","_sys_meta":"simpleclassdiagram.Class","_sys_name":"k17v4n53mu00e","_sys_parent_uri":"root.classes","attr":{},"name":"counter_clerk","operation":{},"srcAssociations":{"k17v4n53mu00m":{"_sys_exist":true,"_sys_id":"","_sys_meta":"simpleclassdiagram.Association","_sys_name":"k17v4n53mu00m","_sys_parent_uri":"root.classes.k17v4n53mu00e.srcAssociations","source":"root.classes.k17v4n53mu00e","target":"root.classes.k17v4n53mu00g"},"k17v4n53mu00o":{"_sys_exist":true,"_sys_id":"","_sys_meta":"simpleclassdiagram.Association","_sys_name":"k17v4n53mu00o","_sys_parent_uri":"root.classes.k17v4n53mu00e.srcAssociations","source":"root.classes.k17v4n53mu00e","target":"root.classes.k17v4n53mu001"}},"srcGeneralization":{}},"k17v4n53mu00g":{"_sys_exist":true,"_sys_id":"name","_sys_meta":"simpleclassdiagram.Class","_sys_name":"k17v4n53mu00g","_sys_parent_uri":"root.classes","attr":{},"name":"stock_manager","operation":{},"srcAssociations":{"j17v4njgg1005":{"_sys_exist":true,"_sys_id":"","_sys_meta":"simpleclassdiagram.Association","_sys_name":"j17v4njgg1005","_sys_parent_uri":"root.classes.k17v4n53mu00g.srcAssociations","source":"root.classes.k17v4n53mu00g","target":"root.classes.k17v4n53mu00k"},"j17v4njgg1007":{"_sys_exist":true,"_sys_id":"","_sys_meta":"simpleclassdiagram.Association","_sys_name":"j17v4njgg1007","_sys_parent_uri":"root.classes.k17v4n53mu00g.srcAssociations","source":"root.classes.k17v4n53mu00g","target":"root.classes.k17v4n53mu00i"}},"srcGeneralization":{}},"k17v4n53mu00i":{"_sys_exist":true,"_sys_id":"name","_sys_meta":"simpleclassdiagram.Class","_sys_name":"k17v4n53mu00i","_sys_parent_uri":"root.classes","attr":{},"name":"DVD","operation":{},"srcAssociations":{},"srcGeneralization":{}},"k17v4n53mu00k":{"_sys_exist":true,"_sys_id":"name","_sys_meta":"simpleclassdiagram.Class","_sys_name":"k17v4n53mu00k","_sys_parent_uri":"root.classes","attr":{},"name":"search_device","operation":{},"srcAssociations":{},"srcGeneralization":{}}}}}},"name":"master","parent":{"branch":"","version":""}}},"created_date":"2013-07-10T16:46:37.233Z","group_id":null,"group_list":[],"group_list_r":[],"last_modified_user":"51636b6a6dcb72db18000002","list":["51636b6a6dcb72db18000002"],"list_r":[],"name":"large2","owner_id":"51636b6a6dcb72db18000002","owner_name":"河崎敏弥","projectkey":"219abe31a105b13ff6a27ca8014089bf","toolVersion":5,"toolkey":"simpleclassdiagram","updated_date":"2013-07-10T16:46:44.416Z","visibillity":"list"}